zensols/nlp/resources/component.conf
zensols/nlp/resources/decorator.conf
zensols/nlp/resources/mapper.conf
zensols/nlp/resources/obj.conf
zensols/nlp/resources/score.yml
zensols/nlp/resources/serial.conf
zensols/nlp/__init__.py
zensols/nlp/chunker.py
zensols/nlp/combine.py
zensols/nlp/component.py
zensols/nlp/container.py
zensols/nlp/dataframe.py
zensols/nlp/decorate.py
zensols/nlp/domain.py
zensols/nlp/index.py
zensols/nlp/nerscore.py
zensols/nlp/norm.py
zensols/nlp/parser.py
zensols/nlp/score.py
zensols/nlp/serial.py
zensols/nlp/spannorm.py
zensols/nlp/sparser.py
zensols/nlp/stemmer.py
zensols/nlp/tok.py
zensols_nlp-1.13.1.dist-info/METADATA
zensols_nlp-1.13.1.dist-info/WHEEL
zensols_nlp-1.13.1.dist-info/licenses/LICENSE.md
zensols_nlp-1.13.1.dist-info/RECORD
