Metadata-Version: 2.3
Name: zensols_nlp
Version: 1.13.1
Summary: This framework wraps the spaCy framework and creates light weight features in a class hierarchy that reflects the structure of natural language
Project-URL: Homepage, https://github.com/plandes/nlp
Project-URL: Documentation, https://plandes.github.io/nlp
Project-URL: Repository, https://github.com/plandes/nlp.git
Project-URL: Issues, https://github.com/plandes/nlp/issues
Project-URL: Changelog, https://github.com/plandes/nlp/blob/master/CHANGELOG.md
Author-email: Paul Landes <landes@mailc.net>
License: MIT
Keywords: nlp,spacy,tooling
Requires-Python: <3.15,>=3.11
Requires-Dist: interlap~=0.2.7
Requires-Dist: nltk~=3.7
Requires-Dist: numpy~=2.4.0
Requires-Dist: spacy~=3.8.11
Requires-Dist: zensols-util~=1.16.3
